{
  "_class": "group",
  "booleanOperation": -1,
  "do_objectID": "43D5D93F-EC76-4554-BC98-42558ADD93B1",
  "exportOptions": {
    "_class": "exportOptions",
    "exportFormats": [
    ],
    "includedLayerIds": [
    ],
    "layerOptions": 0,
    "shouldTrim": false
  },
  "frame": {
    "_class": "rect",
    "constrainProportions": false,
    "height": 40,
    "width": 63,
    "x": 261,
    "y": 144
  },
  "hasClickThrough": false,
  "isFixedToViewport": false,
  "isFlippedHorizontal": false,
  "isFlippedVertical": false,
  "isLocked": false,
  "isVisible": true,
  "layerListExpandedType": 0,
  "layers": [
    {
      "class": "text",
      "id": "85AFA5B8-0ACE-4BFA-A8C8-8DCEAB24B5C9"
    },
    {
      "class": "text",
      "id": "76206A23-2F72-4BD5-AD7A-60672AAA8464"
    },
    {
      "class": "shapeGroup",
      "id": "52C2393F-1F2D-4CD7-B8BD-F77F0BB7925E"
    }
  ],
  "name": "Group",
  "nameIsFixed": false,
  "resizingConstraint": 63,
  "resizingType": 0,
  "rotation": 0,
  "shouldBreakMaskChain": false,
  "style": {
    "_class": "style",
    "endMarkerType": 0,
    "miterLimit": 10,
    "startMarkerType": 0,
    "windingRule": 1
  },
  "userInfo": {
    "com.animaapp.stc-sketch-plugin": {
      "kModelPropertiesKey": {
      }
    }
  }
}