{
  "_class": "symbolMaster",
  "backgroundColor": {
    "_class": "color",
    "alpha": 1,
    "blue": 1,
    "do_objectID": "5EB62DA7-D8B5-423C-907D-96CB1D594521",
    "green": 1,
    "red": 1
  },
  "booleanOperation": 0,
  "changeIdentifier": 343,
  "do_objectID": "5CC3F505-8AB1-4536-8451-4F3FE167A95C",
  "exportOptions": {
    "_class": "exportOptions",
    "do_objectID": "B9561DE9-36A9-4C58-B659-F53EFC3D1D51",
    "exportFormats": [
    ],
    "includedLayerIds": [
    ],
    "layerOptions": 0,
    "shouldTrim": false
  },
  "frame": {
    "_class": "rect",
    "constrainProportions": false,
    "do_objectID": "2C65CE2B-F7F5-4518-8339-E5D7B865B205",
    "height": 160,
    "width": 160,
    "x": 360,
    "y": 520
  },
  "hasBackgroundColor": false,
  "hasClickThrough": true,
  "horizontalRulerData": {
    "_class": "rulerData",
    "base": 0,
    "do_objectID": "89920CA7-CBCA-462E-A462-CFBDFEE3BB7D",
    "guides": [
    ]
  },
  "includeBackgroundColorInExport": true,
  "includeBackgroundColorInInstance": false,
  "includeInCloudUpload": true,
  "isFixedToViewport": false,
  "isFlippedHorizontal": false,
  "isFlippedVertical": false,
  "isFlowHome": false,
  "isLocked": false,
  "isVisible": true,
  "layerListExpandedType": 1,
  "layers": [
    {
      "class": "shapeGroup",
      "id": "2DB4DC89-4C5E-48B2-9336-27F3D6B70511"
    }
  ],
  "name": "color / primary / 3",
  "nameIsFixed": true,
  "originalObjectID": "35A20551-DF33-4C3F-91BB-2CD028688CC7",
  "resizesContent": false,
  "resizingConstraint": 63,
  "resizingType": 0,
  "rotation": 0,
  "shouldBreakMaskChain": true,
  "style": {
    "_class": "style",
    "do_objectID": "950BC190-591C-4112-82BC-B947DF9C68C1",
    "endMarkerType": 0,
    "miterLimit": 10,
    "startMarkerType": 0,
    "windingRule": 1
  },
  "symbolID": "6CF16665-A45E-4D50-B3BC-7359E05ADE4A",
  "userInfo": {
    "com.animaapp.stc-sketch-plugin": {
      "kModelPropertiesKey": {
      }
    }
  },
  "verticalRulerData": {
    "_class": "rulerData",
    "base": 0,
    "do_objectID": "5E3BF320-2F96-467D-98B6-3B35DE159314",
    "guides": [
    ]
  }
}