{
  "_class": "group",
  "booleanOperation": -1,
  "do_objectID": "D63595EE-874D-428F-AF7F-9A246001AF52",
  "exportOptions": {
    "_class": "exportOptions",
    "exportFormats": [
    ],
    "includedLayerIds": [
    ],
    "layerOptions": 0,
    "shouldTrim": false
  },
  "frame": {
    "_class": "rect",
    "constrainProportions": false,
    "height": 48,
    "width": 343,
    "x": 16,
    "y": 304
  },
  "hasClickThrough": false,
  "isFixedToViewport": false,
  "isFlippedHorizontal": false,
  "isFlippedVertical": false,
  "isLocked": false,
  "isVisible": true,
  "layerListExpandedType": 2,
  "layers": [
    {
      "class": "shapeGroup",
      "id": "191524AB-180A-40E0-872F-1DB95703C5B9"
    },
    {
      "class": "symbolInstance",
      "id": "F669A358-24F7-4F5F-A664-89F9802C3EF9"
    },
    {
      "class": "text",
      "id": "86222F3B-F026-4270-B92F-EB54AD75617C"
    }
  ],
  "name": "Group 5",
  "nameIsFixed": false,
  "resizingConstraint": 63,
  "resizingType": 0,
  "rotation": 0,
  "shouldBreakMaskChain": false,
  "style": {
    "_class": "style",
    "endMarkerType": 0,
    "miterLimit": 10,
    "startMarkerType": 0,
    "windingRule": 1
  },
  "userInfo": {
    "com.animaapp.stc-sketch-plugin": {
      "kModelPropertiesKey": {
      }
    }
  }
}